thames/__init__.py
thames/_version.py
thames/_version.pyi
thames/py.typed
thames-0.0.0.dist-info/licenses/LICENSE
thames-0.0.0.dist-info/METADATA
thames-0.0.0.dist-info/WHEEL
thames-0.0.0.dist-info/top_level.txt
thames-0.0.0.dist-info/RECORD
