Metadata-Version: 2.4
Name: thames
Version: 0.0.0
Summary: SDK for Quantum Error Correction
Author-email: Riverlane Ltd <guen.prawiro@riverlane.com>
License-Expression: MIT
Project-URL: Homepage, https://github.com/riverlane/thames
Project-URL: Bug Tracker, https://github.com/riverlane/thames/issues
Project-URL: Discussions, https://github.com/riverlane/thames/discussions
Project-URL: Changelog, https://github.com/riverlane/thames/releases
Classifier: Development Status :: 1 - Planning
Classifier: Intended Audience :: Science/Research
Classifier: Intended Audience :: Developers
Classifier: Operating System :: OS Independent
Classifier: Programming Language :: Python
Classifier: Programming Language :: Python :: 3
Classifier: Programming Language :: Python :: 3 :: Only
Classifier: Programming Language :: Python :: 3.9
Classifier: Programming Language :: Python :: 3.10
Classifier: Programming Language :: Python :: 3.11
Classifier: Programming Language :: Python :: 3.12
Classifier: Programming Language :: Python :: 3.13
Classifier: Topic :: Scientific/Engineering
Classifier: Typing :: Typed
Requires-Python: >=3.9
License-File: LICENSE
Dynamic: license-file
